amplitude/__init__.py
amplitude/amplitude.py
amplitude/apps.py
amplitude/middleware.py
amplitude/settings.py
amplitude/utils.py
django_amplitude-0.8.1.dist-info/LICENSE.md
django_amplitude-0.8.1.dist-info/METADATA
django_amplitude-0.8.1.dist-info/WHEEL
django_amplitude-0.8.1.dist-info/RECORD
