Metadata-Version: 2.1
Name: django-amplitude
Version: 0.8.1
Summary: Integration between Django and Amplitude
Home-page: https://github.com/pyepye/django-amplitude
License: MIT
Keywords: amplitude,analytics,product analytics,saas
Author: Matt Pye
Author-email: pyematt@gmail.com
Requires-Python: >=3.6,<4.0
Classifier: License :: OSI Approved :: MIT License
Classifier: Programming Language :: Python :: 3
Classifier: Programming Language :: Python :: 3.6
Classifier: Programming Language :: Python :: 3.7
Classifier: Programming Language :: Python :: 3.8
Classifier: Programming Language :: Python :: 3.9
Classifier: Programming Language :: Python :: 3.10
Classifier: Programming Language :: Python :: 3.11
Requires-Dist: Django (>=2.1)
Requires-Dist: httpx (>=0.13.2)
Requires-Dist: user-agents (>=2.1)
Project-URL: Repository, https://github.com/pyepye/django-amplitude
